{
    "patches": [
        {
            "label": "2025-11-16_10-55-54",
            "content": "@@ -493,940 +493,130 @@\n ity%0A\n-    def _verify_index(self, index:int):%0A        if index %3C 0 or index %3E= len(self.__seats):%0A            raise Exception(%22fail: cadeira nao existe%22)%0A        %0A%0A%0A%0A    def _find_client(self, idd:str):%0A        for i in range(len(self.__seats)):%0A            client = self.__seats%5Bi%5D%0A            if client is not None and client.get_id() == idd:%0A                return i%0A        return -1%0A    %0A    def reserve(self, idd:str, phone:int, index:int):%0A        self._verify_index(index)%0A        if self.__seats%5Bindex%5D is not None:%0A            raise Exception(%22fail: cadeira ja esta ocupada%22)%0A        if self._find_client(idd) is not None:%0A            raise Exception(%22fail: cliente ja esta no cinema%22)%0A        self.__seats%5Bindex%5D = Client(idd, phone)%0A%0A    def cancel(self, idd:str):%0A        index = self._find_client(idd)%0A        if index == -1:%0A            raise Exception(%22fail: cliente nao esta no cinema%22)%0A        self.__seats%5Bindex%5D = None\n+%0A    def reserve(self, idd:str, phone:int, index:int):%0A        print(%22%22)%0A%0A    def cancel(self, idd:str):%0A        print(%22%22)\n %0A%0A  \n@@ -631,20 +631,16 @@\n t_seats(\n-self\n ):%0A     \n@@ -653,605 +653,5 @@\n urn \n-self.__seats%0A    %0A    def __str__(self):%0A        a = %5B%5D%0A        for i in self.__seats:%0A            if i is None:%0A                a.append(%22-%22)%0A            else:%0A                a.append(str(i))%0A%0A        return %22%5B%22+ %22 %22.join(a) + %22%5D%22%0A%0Adef main():%0A    theater = Theater(5)%0A    print(theater)%0A    theater.reserve(%22123%22, 9999, 0)%0A    theater.reserve(%22456%22, 8888, 1)%0A    print(theater)%0A    theater.cancel(%22123%22)%0A    print(theater)%0A    try:%0A        theater.reserve(%22456%22, 7777, 1)%0A    except Exception as e:%0A        print(e)%0A    try:%0A        theater.cancel(%22789%22)%0A    except Exception as e:%0A        print(e)\n+%0A\n",
            "lines": "30"
        },
        {
            "label": "2025-11-16_15-16-32",
            "content": "@@ -28,38 +28,16 @@\n t__(self\n-, idd: str, phone: int\n ):%0A     \n@@ -49,22 +49,20 @@\n lf.__idd\n- = idd\n+:str\n %0A       \n@@ -70,32 +70,28 @@\n self.__phone\n- = phone\n+:int\n %0A%0A    def ge\n@@ -133,21 +133,16 @@\n __phone%0A\n-    %0A\n     def \n@@ -163,17 +163,16 @@\n , phone:\n- \n int):%0A  \n@@ -249,14 +249,8 @@\n __id\n-d%0A    \n %0A   \n@@ -263,36 +263,35 @@\n et_id(self, idd:\n- str\n+int\n ):%0A        self.\n@@ -377,17 +377,16 @@\n %7D%22%0A    %0A\n-%0A\n class Th\n@@ -424,17 +424,16 @@\n apacity:\n- \n int):%0A  \n@@ -451,17 +451,16 @@\n __seats:\n- \n list%5BCli\n@@ -483,11 +483,9 @@\n one%5D\n- * \n+*\n capa\n@@ -489,17 +489,16 @@\n apacity%0A\n-%0A\n     def \n@@ -515,33 +515,32 @@\n dex(self, index:\n- \n int):%0A        if\n@@ -637,16 +637,27 @@\n xiste%22)%0A\n+        %0A%0A%0A\n %0A    def\n@@ -672,33 +672,32 @@\n lient(self, idd:\n- \n str):%0A        fo\n@@ -703,30 +703,59 @@\n or i\n-, client in enumerate(\n+ in range(len(self.__seats)):%0A            client = \n self\n@@ -754,34 +754,35 @@\n t = self.__seats\n-):\n+%5Bi%5D\n %0A            if \n@@ -902,17 +902,16 @@\n lf, idd:\n- \n str, pho\n@@ -913,17 +913,16 @@\n , phone:\n- \n int, ind\n@@ -924,17 +924,16 @@\n , index:\n- \n int):%0A  \n@@ -964,17 +964,16 @@\n (index)%0A\n-%0A\n         \n@@ -1065,25 +1065,24 @@\n a ocupada%22)%0A\n-%0A\n         if s\n@@ -1107,13 +1107,19 @@\n dd) \n-!= -1\n+is not None\n :%0A  \n@@ -1171,33 +1171,32 @@\n sta no cinema%22)%0A\n-%0A\n         self.__s\n@@ -1254,17 +1254,16 @@\n lf, idd:\n- \n str):%0A  \n@@ -1299,17 +1299,16 @@\n nt(idd)%0A\n-%0A\n         \n@@ -1387,17 +1387,16 @@\n inema%22)%0A\n-%0A\n         \n@@ -1512,19 +1512,17 @@\n         \n-out\n+a\n  = %5B%5D%0A  \n@@ -1531,22 +1531,17 @@\n     for \n-client\n+i\n  in self\n@@ -1561,30 +1561,25 @@\n          if \n-client\n+i\n  is None:%0A  \n@@ -1584,35 +1584,33 @@\n                 \n-out\n+a\n .append(%22-%22)%0A   \n@@ -1640,19 +1640,17 @@\n         \n-out\n+a\n .append(\n@@ -1657,17 +1657,13 @@\n str(\n-client\n+i\n ))%0A\n+%0A\n     \n@@ -1676,17 +1676,16 @@\n turn %22%5B%22\n- \n + %22 %22.jo\n@@ -1691,11 +1691,9 @@\n oin(\n-out\n+a\n ) + \n@@ -1697,17 +1697,16 @@\n  + %22%5D%22%0A%0A\n-%0A\n def main\n@@ -1745,33 +1745,32 @@\n  print(theater)%0A\n-%0A\n     theater.rese\n@@ -1840,25 +1840,24 @@\n nt(theater)%0A\n-%0A\n     theater.\n@@ -1889,17 +1889,16 @@\n heater)%0A\n-%0A\n     try:\n@@ -1982,17 +1982,16 @@\n rint(e)%0A\n-%0A\n     try:\n@@ -2068,14 +2068,4 @@\n t(e)\n-%0A%0A%0Amain()%0A\n",
            "lines": "78"
        },
        {
            "label": "2025-11-16_15-19-26",
            "content": "@@ -1752,367 +1752,236 @@\n     \n-while True:%0A        line = input()%0A        print(%22$%22 + line)%0A        args = line.split(%22 %22)%0A        if args%5B0%5D == %22init%22:%0A            theater = Theater(int(args%5B1%5D))%0A        elif args%5B0%5D == %22show%22:%0A            print(theater)%0A        elif args%5B0%5D == %22reserve%22:%0A            try:%0A                theater.reserve(str(args%5B1%5D), int(args%5B2%5D), int(args%5B3%5D))%0A        \n+theater = Theater(5)%0A    print(theater)%0A%0A    theater.reserve(%22123%22, 9999, 0)%0A    theater.reserve(%22456%22, 8888, 1)%0A    print(theater)%0A%0A    theater.cancel(%22123%22)%0A    print(theater)%0A%0A    try:%0A        theater.reserve(%22456%22, 7777, 1)%0A\n     \n@@ -1999,32 +1999,24 @@\n ption as e:%0A\n-        \n         prin\n@@ -2024,50 +2024,9 @@\n (e)%0A\n-        elif args%5B0%5D == %22cancel%22:%0A        \n+%0A\n     \n@@ -2030,24 +2030,16 @@\n    try:%0A\n-        \n         \n@@ -2057,30 +2057,15 @@\n cel(\n-str(args%5B1%5D))%0A        \n+%22789%22)%0A\n     \n@@ -2087,24 +2087,16 @@\n n as e:%0A\n-        \n         \n@@ -2108,114 +2108,9 @@\n (e)%0A\n-        elif args%5B0%5D == %22end%22:%0A            break%0A        else:%0A            print(%22fail: comando invalido%22)\n+%0A\n %0Amai\n",
            "lines": "90"
        },
        {
            "label": "2025-11-16_15-21-31",
            "content": "@@ -1748,28 +1748,8 @@\n ():%0A\n-    theater = Nones%0A\n     \n",
            "lines": "91"
        },
        {
            "label": "2025-11-16_15-25-01",
            "content": "@@ -1762,16 +1762,17 @@\n r = None\n+s\n %0A    whi\n",
            "lines": "92"
        },
        {
            "label": "2025-11-16_15-25-06",
            "content": "@@ -1759,17 +1759,15 @@\n ater\n-: Theater\n+ = None\n %0A   \n",
            "lines": "92"
        },
        {
            "label": "2025-11-16_15-25-19",
            "content": "@@ -1764,21 +1764,16 @@\n  Theater\n- = %5B%5D\n %0A    whi\n",
            "lines": "92"
        },
        {
            "label": "2025-11-16_15-25-27",
            "content": "class Client:\n    def __init__(self, idd: str, phone: int):\n        self.__idd = idd\n        self.__phone = phone\n\n    def get_phone(self):\n        return self.__phone\n    \n    def set_phone(self, phone: int):\n        self.__phone = phone\n\n    def get_id(self):\n        return self.__idd\n    \n    def set_id(self, idd: str):\n        self.__idd = idd\n\n    def __str__(self):\n        return f\"{self.__idd}:{self.__phone}\"\n    \n\nclass Theater:\n    def __init__(self, capacity: int):\n        self.__seats: list[Client | None] = [None] * capacity\n\n    def _verify_index(self, index: int):\n        if index < 0 or index >= len(self.__seats):\n            raise Exception(\"fail: cadeira nao existe\")\n\n    def _find_client(self, idd: str):\n        for i, client in enumerate(self.__seats):\n            if client is not None and client.get_id() == idd:\n                return i\n        return -1\n    \n    def reserve(self, idd: str, phone: int, index: int):\n        self._verify_index(index)\n\n        if self.__seats[index] is not None:\n            raise Exception(\"fail: cadeira ja esta ocupada\")\n\n        if self._find_client(idd) != -1:\n            raise Exception(\"fail: cliente ja esta no cinema\")\n\n        self.__seats[index] = Client(idd, phone)\n\n    def cancel(self, idd: str):\n        index = self._find_client(idd)\n\n        if index == -1:\n            raise Exception(\"fail: cliente nao esta no cinema\")\n\n        self.__seats[index] = None\n\n    def get_seats(self):\n        return self.__seats\n    \n    def __str__(self):\n        out = []\n        for client in self.__seats:\n            if client is None:\n                out.append(\"-\")\n            else:\n                out.append(str(client))\n        return \"[\" + \" \".join(out) + \"]\"\n\n\ndef main():\n    theater: Theater = []\n    while True:\n        line = input()\n        print(\"$\" + line)\n        args = line.split(\" \")\n        if args[0] == \"init\":\n            theater = Theater(int(args[1]))\n        elif args[0] == \"show\":\n            print(theater)\n        elif args[0] == \"reserve\":\n            try:\n                theater.reserve(str(args[1]), int(args[2]), int(args[3]))\n            except Exception as e:\n                print(e)\n        elif args[0] == \"cancel\":\n            try:\n                theater.cancel(str(args[1]))\n            except Exception as e:\n                print(e)\n        elif args[0] == \"end\":\n            break\n        else:\n            print(\"fail: comando invalido\")\nmain()\n",
            "lines": "92"
        }
    ]
}